{
  "main": {
    "id": "cc046320f08a0801",
    "type": "split",
    "children": [
      {
        "id": "95acf50f838a5240",
        "type": "tabs",
        "children": [
          {
            "id": "ed21549823f75445",
            "type": "leaf",
            "state": {
              "type": "canvas",
              "state": {
                "file": "GAMEPLAY_MainStory/Cselekmény.canvas",
                "viewState": {
                  "x": 440,
                  "y": -1680,
                  "zoom": -1.430834841570189
                }
              }
            }
          }
        ]
      }
    ],
    "direction": "vertical"
  },
  "left": {
    "id": "a413f96bf7f3bd86",
    "type": "split",
    "children": [
      {
        "id": "59f5c4af49f24f13",
        "type": "tabs",
        "children": [
          {
            "id": "4778091b8f5e8a57",
            "type": "leaf",
            "state": {
              "type": "file-explorer",
              "state": {
                "sortOrder": "alphabetical"
              }
            }
          },
          {
            "id": "dedc6a63457a93f2",
            "type": "leaf",
            "state": {
              "type": "search",
              "state": {
                "query": "",
                "matchingCase": false,
                "explainSearch": false,
                "collapseAll": false,
                "extraContext": false,
                "sortOrder": "alphabetical"
              }
            }
          },
          {
            "id": "5fd1896aa695cc7f",
            "type": "leaf",
            "state": {
              "type": "bookmarks",
              "state": {}
            }
          }
        ]
      }
    ],
    "direction": "horizontal",
    "width": 427.5
  },
  "right": {
    "id": "79fe7c6fd4fa9545",
    "type": "split",
    "children": [
      {
        "id": "3c20a9614e0fb4a2",
        "type": "tabs",
        "children": [
          {
            "id": "afa8c7a9beceba7f",
            "type": "leaf",
            "state": {
              "type": "backlink",
              "state": {
                "file": "GAMEPLAY_MainStory/Cselekmény.canvas",
                "collapseAll": false,
                "extraContext": false,
                "sortOrder": "alphabetical",
                "showSearch": false,
                "searchQuery": "",
                "backlinkCollapsed": false,
                "unlinkedCollapsed": true
              }
            }
          },
          {
            "id": "edeb86dfaa4182ed",
            "type": "leaf",
            "state": {
              "type": "outgoing-link",
              "state": {
                "file": "GAMEPLAY_MainStory/Cselekmény.canvas",
                "linksCollapsed": false,
                "unlinkedCollapsed": true
              }
            }
          },
          {
            "id": "2c163c04b61dba21",
            "type": "leaf",
            "state": {
              "type": "tag",
              "state": {
                "sortOrder": "frequency",
                "useHierarchy": true
              }
            }
          },
          {
            "id": "506e1bc0e43bff01",
            "type": "leaf",
            "state": {
              "type": "outline",
              "state": {
                "file": "GAMEPLAY_MainStory/Cselekmény.canvas"
              }
            }
          }
        ],
        "currentTab": 3
      }
    ],
    "direction": "horizontal",
    "width": 300,
    "collapsed": true
  },
  "left-ribbon": {
    "hiddenItems": {
      "switcher:Open quick switcher": false,
      "graph:Open graph view": false,
      "canvas:Create new canvas": false,
      "daily-notes:Open today's daily note": false,
      "templates:Insert template": false,
      "command-palette:Open command palette": false
    }
  },
  "active": "4778091b8f5e8a57",
  "lastOpenFiles": [
    "SOJOURN/GAMEPLAY_Demo/Cselekmény_Párbeszédek_Puzzles.md",
    "SOJOURN/WORLDBUILDING/Karakterek.md",
    "SOJOURN/SCRIPTS/Door.md",
    "SOJOURN/GAMEPLAY_MainStory/Cselekmény_Párbeszédek_Puzzles.md",
    "SOJOURN/GAMEPLAY_MainStory/Cselekmény.canvas",
    "SOJOURN/GAMEPLAY_MECHANIKÁK/Swap_Ability.canvas",
    "SOJOURN/WORLDBUILDING/Helyszínek.md",
    "SOJOURN/WORLDBUILDING/Story.md",
    "KARAKTER BRAINSTORM/Emlyn.canvas",
    "KARAKTER BRAINSTORM/SABLON.canvas",
    "SOJOURN/GAMEPLAY_Demo/Cselekmény.canvas",
    "KARAKTER BRAINSTORM/JUNGIAN Archetípusok.png",
    "Untitled.canvas",
    "KARAKTER BRAINSTORM/Enigma Infinitum/Koda.canvas",
    "SOJOURN/GAMEPLAY_MECHANIKÁK",
    "SOJOURN/GAMEPLAY_Demo",
    "SOJOURN/WORLDBUILDING/Képek/Three Act Structure.png",
    "ARIA HAYES.md",
    "Aria Hayes.md",
    "SOJOURN/GAMEPLAY_MainStory",
    "KARAKTER BRAINSTORM/Enigma Infinitum/Amber.canvas",
    "KARAKTER BRAINSTORM/Enigma Infinitum/Joshua.canvas",
    "KARAKTER BRAINSTORM/Enigma Infinitum/June.canvas",
    "KARAKTER BRAINSTORM/Enigma Infinitum/1.Felépítés.png",
    "KARAKTER BRAINSTORM/Enigma Infinitum/Amber.md",
    "KARAKTER BRAINSTORM/Enigma Infinitum/June.md",
    "KARAKTER BRAINSTORM/Enigma Infinitum/Joshua.md",
    "KARAKTER BRAINSTORM/Enigma Infinitum/Koda.md",
    "Untitled 2",
    "Untitled 1",
    "KARAKTER BRAINSTORM/Enigma Infinitum",
    "KARAKTER BRAINSTORM/Untitled mindmap.md",
    "KARAKTER BRAINSTORM/Emlyn/Infó.md",
    "KARAKTER BRAINSTORM/Emlyn",
    "KARAKTER BRAINSTORM",
    "SOJOURN",
    "WORLDBUILDING/Szöveg.md",
    "SOJOURN/WORLDBUILDING/Képek",
    "WORLDBUILDING/Mellékszál.md",
    "Chapter 1.md",
    "Pasted image 20240901183045.png",
    "Használat.md"
  ]
}